MANIFEST.in
README
runner
setup.cfg
setup.py
eafsotlogger.egg-info/PKG-INFO
eafsotlogger.egg-info/SOURCES.txt
eafsotlogger.egg-info/dependency_links.txt
eafsotlogger.egg-info/requires.txt
eafsotlogger.egg-info/top_level.txt
soteventlogger/__init__.py
soteventlogger/soteventlogger.py