Metadata-Version: 1.1
Name: eafsotlogger
Version: 1.1
Summary: SOT Library, Maintain log in casandra database using python script.
Home-page: http://www.netcore.in/
Author: Raj
Author-email: raj.pawar@netcore.co.in
License: UNKNOWN
Platform: UNKNOWN
Classifier: Development Status :: 4 - Beta
Classifier: Environment :: X11 Applications :: GTK
Classifier: Intended Audience :: End Users/Desktop
Classifier: Intended Audience :: Developers
Classifier: License :: OSI Approved :: GNU General Public License (GPL)
Classifier: Operating System :: POSIX :: Linux
Classifier: Programming Language :: Python
Classifier: Topic :: Desktop Environment
Classifier: Topic :: Text Processing :: Fonts
